ssptools/BSData.py
ssptools/__init__.py
ssptools/compare.py
ssptools/eigenvalues.py
ssptools/kpaths.py
ssptools/io/__init__.py
ssptools/io/main.py
ssptools-0.4.1.data/scripts/2POS.py
ssptools-0.4.1.data/scripts/appendKPaths.py
ssptools-0.4.1.data/scripts/compareEV.py
ssptools-0.4.1.data/scripts/plotBS.py
ssptools-0.4.1.data/scripts/sortPOS.py
ssptools-0.4.1.dist-info/LICENSE
ssptools-0.4.1.dist-info/METADATA
ssptools-0.4.1.dist-info/WHEEL
ssptools-0.4.1.dist-info/top_level.txt
ssptools-0.4.1.dist-info/RECORD
