Metadata-Version: 2.1
Name: ssptools
Version: 0.4.1
Summary: Various specialized tools for working with the input and output of VASP
Home-page: https://github.com/martin-eom/ssptools
Author: Martin Keller
Classifier: Programming Language :: Python :: 3
Classifier: License :: OSI Approved :: MIT License
Classifier: Operating System :: OS Independent
Requires-Python: >=3.4
License-File: LICENSE
Requires-Dist: ase
Requires-Dist: matplotlib
Requires-Dist: numpy
Requires-Dist: pymatgen
